LICENSE
README.txt
setup.cfg
setup.py
bin/zkinitree.py
bin/zkrsync.py
lib/vsc/__init__.py
lib/vsc/zk/__init__.py
lib/vsc/zk/base.py
lib/vsc/zk/depthwalk.py
lib/vsc/zk/zkconfigparser.py
lib/vsc/zk/rsync/__init__.py
lib/vsc/zk/rsync/controller.py
lib/vsc/zk/rsync/destination.py
lib/vsc/zk/rsync/source.py
lib/vsc_zk.egg-info/PKG-INFO
lib/vsc_zk.egg-info/SOURCES.txt
lib/vsc_zk.egg-info/dependency_links.txt
lib/vsc_zk.egg-info/namespace_packages.txt
lib/vsc_zk.egg-info/requires.txt
lib/vsc_zk.egg-info/top_level.txt