Metadata-Version: 2.1
Name: vsc-zk
Version: 2.0.7
Summary: vsc-zk contains scripts to build zookeeper trees and tools using zookeeper.
Home-page: https://github.com/hpcugent/vsc-zk
Download-URL: 
Author: Stijn De Weirdt;Kenneth Waegeman
Author-email: stijn.deweirdt@ugent.be, Kenneth.Waegeman@UGent.be
Maintainer: Stijn De Weirdt;Kenneth Waegeman
Maintainer-email: stijn.deweirdt@ugent.be, Kenneth.Waegeman@UGent.be
License: LGPLv2+
Classifier: License :: OSI Approved :: GNU Lesser General Public License v2 or later (LGPLv2+)
License-File: LICENSE
